brav0/__init__.py
brav0/cli.py
brav0/correction.py
brav0/driver.py
brav0/io.py
brav0/lexsort_op.py
brav0/model.py
brav0/plot.py
brav0/preprocess.py
brav0/rmplanets.py
brav0/rolling.py
brav0/utils.py
brav0-0.2.0.dist-info/LICENSE
brav0-0.2.0.dist-info/METADATA
brav0-0.2.0.dist-info/WHEEL
brav0-0.2.0.dist-info/entry_points.txt
brav0-0.2.0.dist-info/top_level.txt
brav0-0.2.0.dist-info/RECORD
