Metadata-Version: 2.1
Name: brav0
Version: 0.2.0
Summary: Bayesian Radial Velcoity Zero-Point Correction
Home-page: https://github.com/vandalt/brav0
Author: Thomas Vandal
Author-email: thomasvandal@hotmail.com
License: MIT License
Platform: UNKNOWN
License-File: LICENSE
Requires-Dist: numpy
Requires-Dist: scipy
Requires-Dist: pandas
Requires-Dist: astropy
Requires-Dist: matplotlib
Requires-Dist: requests
Requires-Dist: radvel
Requires-Dist: astroquery
Requires-Dist: h5py
Requires-Dist: pymc3
Requires-Dist: arviz
Requires-Dist: xarray
Requires-Dist: pymc3-ext
Requires-Dist: aesara-theano-fallback
Requires-Dist: exoplanet
Requires-Dist: celerite2
Requires-Dist: python-box
Requires-Dist: orbits
Requires-Dist: tqdm
Provides-Extra: dev
Requires-Dist: ipython ; extra == 'dev'
Requires-Dist: jupytext ; extra == 'dev'
Requires-Dist: black ; extra == 'dev'
Requires-Dist: isort ; extra == 'dev'
Requires-Dist: flake8 ; extra == 'dev'
Requires-Dist: ipdb ; extra == 'dev'
Requires-Dist: pytest ; extra == 'dev'
